telegram_wallet_pay/__init__.py
telegram_wallet_pay/client.py
telegram_wallet_pay/constants.py
telegram_wallet_pay/errors.py
telegram_wallet_pay/enums/__init__.py
telegram_wallet_pay/enums/button_name.py
telegram_wallet_pay/enums/currency.py
telegram_wallet_pay/enums/order_status.py
telegram_wallet_pay/enums/request_status.py
telegram_wallet_pay/enums/webhook_message_type.py
telegram_wallet_pay/schemas/__init__.py
telegram_wallet_pay/schemas/_default.py
telegram_wallet_pay/schemas/create_order_request.py
telegram_wallet_pay/schemas/create_order_response.py
telegram_wallet_pay/schemas/get_order_preview_response.py
telegram_wallet_pay/schemas/get_order_reconciliation_list_response.py
telegram_wallet_pay/schemas/money_amount.py
telegram_wallet_pay/schemas/order_amount.py
telegram_wallet_pay/schemas/order_amount_response.py
telegram_wallet_pay/schemas/order_preview.py
telegram_wallet_pay/schemas/order_reconciliation_item.py
telegram_wallet_pay/schemas/order_reconciliation_list.py
telegram_wallet_pay/schemas/payment_option.py
telegram_wallet_pay/schemas/webhook_message.py
telegram_wallet_pay/schemas/webhook_payload.py
telegram_wallet_pay/tools/__init__.py
telegram_wallet_pay/tools/aiohttp.py
telegram_wallet_pay/tools/fastapi.py
telegram_wallet_pay/tools/ip_filter.py
telegram_wallet_pay/tools/signature.py
telegram_wallet_pay/tools/text.py
telegram_wallet_pay-1.0.0.dist-info/METADATA
telegram_wallet_pay-1.0.0.dist-info/WHEEL
telegram_wallet_pay-1.0.0.dist-info/licenses/LICENSE
telegram_wallet_pay-1.0.0.dist-info/RECORD
