Metadata-Version: 2.3
Name: telegram-wallet-pay
Version: 1.0.0
Summary: Async client for Telegram Wallet Pay API
Project-URL: Repository, https://github.com/Olegt0rr/TelegramWalletPay
Project-URL: Documentation, https://docs.wallet.tg/pay/
Author-email: Oleg Abramov <oleg@trueweb.app>
Maintainer-email: Oleg Abramov <oleg@trueweb.app>
License-Expression: MIT
License-File: LICENSE
Keywords: API,Pay,Telegram,Wallet,async
Classifier: Development Status :: 4 - Beta
Classifier: Framework :: AsyncIO
Classifier: Framework :: Pydantic
Classifier: Intended Audience :: Customer Service
Classifier: Intended Audience :: Financial and Insurance Industry
Classifier: License :: OSI Approved :: MIT License
Classifier: Operating System :: MacOS
Classifier: Operating System :: Microsoft :: Windows
Classifier: Operating System :: POSIX :: Linux
Classifier: Programming Language :: Python
Classifier: Programming Language :: Python :: 3.9
Classifier: Programming Language :: Python :: 3.10
Classifier: Programming Language :: Python :: 3.11
Classifier: Programming Language :: Python :: 3.12
Classifier: Programming Language :: Python :: 3.13
Classifier: Programming Language :: Python :: Implementation :: CPython
Classifier: Programming Language :: Python :: Implementation :: PyPy
Classifier: Topic :: Software Development :: Libraries :: Application Frameworks
Classifier: Typing :: Typed
Requires-Python: >=3.9
Requires-Dist: aiohttp<4,>=3.8
Requires-Dist: certifi>=2023
Requires-Dist: pydantic<3,>=2.4
Provides-Extra: dev
Requires-Dist: aiogram<4,>=3.6; extra == 'dev'
Requires-Dist: fastapi-slim<1,>=0.111; extra == 'dev'
Requires-Dist: httpx<1,>=0.27; extra == 'dev'
Requires-Dist: mypy<2,>=1; extra == 'dev'
Requires-Dist: pre-commit<5,>=3; extra == 'dev'
Requires-Dist: ruff<1,>=0; extra == 'dev'
Requires-Dist: uvicorn<1,>=0.29; extra == 'dev'
Provides-Extra: test
Requires-Dist: aresponses<4,>=3; extra == 'test'
Requires-Dist: coverage<8,>=7; extra == 'test'
Requires-Dist: fastapi-slim<1,>=0.111; extra == 'test'
Requires-Dist: httpx<1,>=0.27; extra == 'test'
Requires-Dist: pytest-aiohttp<2,>=1.0; extra == 'test'
Requires-Dist: pytest-asyncio<1,>=0; extra == 'test'
Requires-Dist: pytest-cov<6,>=5; extra == 'test'
Requires-Dist: pytest<9,>=8; extra == 'test'
